pnacos/__init__.py
pnacos/client.py
pnacos/config.py
pnacos-0.1.3.dist-info/LICENSE
pnacos-0.1.3.dist-info/METADATA
pnacos-0.1.3.dist-info/WHEEL
pnacos-0.1.3.dist-info/top_level.txt
pnacos-0.1.3.dist-info/RECORD
