Metadata-Version: 2.1
Name: pnacos
Version: 0.1.3
Summary: 适配nacos模块
Home-page: https://github.com/al6nlee/pnacos
Author: alan
Author-email: al6nlee@gmail.com
License: MIT
Platform: UNKNOWN
Classifier: Intended Audience :: Developers
Classifier: License :: OSI Approved :: MIT License
Classifier: Programming Language :: Python
Classifier: Programming Language :: Python :: 3.9
Classifier: Programming Language :: Python :: 3.10
Classifier: Programming Language :: Python :: 3.11
Classifier: Topic :: Software Development
Requires-Python: >=3.9
License-File: LICENSE
